LICENSE
README.md
pyproject.toml
setup.py
bf16_huffman_infer/__init__.py
bf16_huffman_infer/cudagraph_utils.py
bf16_huffman_infer/cudastream_utils.py
bf16_huffman_infer/functional.py
bf16_huffman_infer/huffman.py
bf16_huffman_infer/ops.py
bf16_huffman_infer/utils.py
bf16_huffman_infer.egg-info/PKG-INFO
bf16_huffman_infer.egg-info/SOURCES.txt
bf16_huffman_infer.egg-info/dependency_links.txt
bf16_huffman_infer.egg-info/requires.txt
bf16_huffman_infer.egg-info/top_level.txt
bf16_huffman_infer/src/bf16_huffman_infer.cpp
bf16_huffman_infer/src/kernel.cu
bf16_huffman_infer/src/bf16_huffman_infer.cpp
bf16_huffman_infer/src/kernel.cu