Metadata-Version: 2.4
Name: bf16_huffman_infer
Version: 0.0.2
Summary: Fused BF16 Huffman GEMV Inference kernel
Home-page: https://github.com/lszxb/bf16_huffman_infer
Author: lszxb
License-File: LICENSE
Requires-Dist: torch
Requires-Dist: transformers
Dynamic: author
Dynamic: description
Dynamic: description-content-type
Dynamic: home-page
Dynamic: license-file
Dynamic: requires-dist
Dynamic: summary
